LICENSE.txt
MANIFEST.in
README.rst
buildout.cfg
setup.py
antispoofing/__init__.py
antispoofing.fvcompetition_icb2015.egg-info/PKG-INFO
antispoofing.fvcompetition_icb2015.egg-info/SOURCES.txt
antispoofing.fvcompetition_icb2015.egg-info/dependency_links.txt
antispoofing.fvcompetition_icb2015.egg-info/entry_points.txt
antispoofing.fvcompetition_icb2015.egg-info/namespace_packages.txt
antispoofing.fvcompetition_icb2015.egg-info/requires.txt
antispoofing.fvcompetition_icb2015.egg-info/top_level.txt
antispoofing/fvcompetition_icb2015/__init__.py
antispoofing/fvcompetition_icb2015/baseline_countermeasure.py
antispoofing/fvcompetition_icb2015/evaluation_results.py