Metadata-Version: 1.1
Name: antispoofing.fvcompetition-icb2015
Version: 2.0.0
Summary: Running the competition results: "The 1st Competition on Counter Measures to Finger Vein Spoofing Attacks".
Home-page: https://github.com/bioidiap/antispoofing.fvcompetition_icb2015.git
Author: Pedro Tome
Author-email: pedro.tome@idiap.ch
License: LICENSE.txt
Platform: UNKNOWN
Classifier: Framework :: Bob
Classifier: Development Status :: 4 - Beta
Classifier: Intended Audience :: Science/Research
Classifier: License :: OSI Approved :: GNU General Public License v3 (GPLv3)
Classifier: Natural Language :: English
Classifier: Programming Language :: Python :: 2.7
Classifier: Environment :: Console
Classifier: Framework :: Buildout
Classifier: Topic :: Scientific/Engineering
